gapp/SessionState.py
gapp/__init__.py
gapp/app.py
gapp/location.py
gapp/plot.py
gplot-3.0.data/scripts/gplot
gplot-3.0.dist-info/LICENCE
gplot-3.0.dist-info/METADATA
gplot-3.0.dist-info/WHEEL
gplot-3.0.dist-info/top_level.txt
gplot-3.0.dist-info/RECORD
