Metadata-Version: 2.1
Name: gplot
Version: 3.0
Summary: A  python library to plot charts from google sheet
Home-page: https://github.com/spctr01/gplot
Author: rakshit kumar
Author-email: rakshitkhpi@example.com
License: UNKNOWN
Platform: UNKNOWN
Classifier: Programming Language :: Python :: 3
Classifier: License :: OSI Approved :: MIT License
Classifier: Operating System :: OS Independent
Requires-Python: >=3.6
Requires-Dist: streamlit
Requires-Dist: plotly
Requires-Dist: pandas
